constrainthg/__init__.py
constrainthg/hypergraph.py
constrainthg/relations.py
constrainthg-0.3.1.dist-info/licenses/LICENSE
constrainthg-0.3.1.dist-info/METADATA
constrainthg-0.3.1.dist-info/WHEEL
constrainthg-0.3.1.dist-info/entry_points.txt
constrainthg-0.3.1.dist-info/top_level.txt
constrainthg-0.3.1.dist-info/RECORD
