Metadata-Version: 2.4
Name: constrainthg
Version: 0.3.1
Summary: Kernel for building and simulating constraint hypergraphs.
Author-email: John Morris <constrainthg@gmail.com>
License-Expression: Apache-2.0
Project-URL: homepage, https://constrainthg.readthedocs.io/en/latest/
Project-URL: documentation, https://constrainthg.readthedocs.io/en/latest/api/index.html
Project-URL: repository, https://github.com/jmorris335/ConstraintHg
Project-URL: issues, https://github.com/jmorris335/ConstraintHg/issues
Keywords: hypergraphs,systems engineering,modeling,simulation
Classifier: Development Status :: 3 - Alpha
Classifier: Programming Language :: Python
Requires-Python: >=3.1
License-File: LICENSE
Requires-Dist: numpy
Dynamic: license-file
